RTFD/__init__.py
RTFD/cache.py
RTFD/chunking.py
RTFD/config_generator.py
RTFD/content_utils.py
RTFD/server.py
RTFD/token_counter.py
RTFD/utils.py
RTFD/providers/__init__.py
RTFD/providers/base.py
RTFD/providers/crates.py
RTFD/providers/dockerhub.py
RTFD/providers/gcp.py
RTFD/providers/github.py
RTFD/providers/godocs.py
RTFD/providers/npm.py
RTFD/providers/pypi.py
RTFD/providers/zig.py
rtfd_mcp-1.2.2.dist-info/METADATA
rtfd_mcp-1.2.2.dist-info/WHEEL
rtfd_mcp-1.2.2.dist-info/entry_points.txt
rtfd_mcp-1.2.2.dist-info/top_level.txt
rtfd_mcp-1.2.2.dist-info/RECORD
