Metadata-Version: 2.4
Name: rtfd-mcp
Version: 1.2.2
Summary: MCP server for real-time library documentation access across multiple package ecosystems.
Author-email: Amit Serper <amit@example.com>
License-Expression: MIT
Project-URL: Homepage, https://github.com/aserper/RTFD
Project-URL: Repository, https://github.com/aserper/RTFD.git
Project-URL: Issues, https://github.com/aserper/RTFD/issues
Project-URL: Documentation, https://github.com/aserper/RTFD#readme
Keywords: mcp,documentation,pypi,npm,crates,godocs,docker,github
Classifier: Development Status :: 4 - Beta
Classifier: Intended Audience :: Developers
Classifier: Operating System :: OS Independent
Classifier: Programming Language :: Python :: 3
Classifier: Programming Language :: Python :: 3.10
Classifier: Programming Language :: Python :: 3.11
Classifier: Programming Language :: Python :: 3.12
Classifier: Programming Language :: Python :: 3.13
Classifier: Topic :: Software Development :: Libraries
Requires-Python: >=3.10
Requires-Dist: mcp>=1.22.0
Requires-Dist: httpx>=0.28.1
Requires-Dist: beautifulsoup4>=4.14.3
Requires-Dist: markdownify>=1.2.2
Requires-Dist: docutils>=0.22.3
Requires-Dist: tiktoken>=0.12.0
Requires-Dist: loguru>=0.7.3
Provides-Extra: dev
Requires-Dist: pytest>=7.0; extra == "dev"
Requires-Dist: pytest-asyncio>=0.21.0; extra == "dev"
Requires-Dist: pytest-cov>=4.0; extra == "dev"
Requires-Dist: pytest-recording>=0.13.0; extra == "dev"
Requires-Dist: ruff>=0.2.0; extra == "dev"
Requires-Dist: python-semantic-release>=9.0.0; extra == "dev"
